fastapi_test.py
pybtocs/__init__.py
pybtocs/__main__.py
pybtocs/cli.py
pybtocs/config/__init__.py
pybtocs/config/core.py
pybtocs/context/__init__.py
pybtocs/context/core.py
pybtocs/context/session.py
pybtocs/context/user.py
pybtocs/interfaces/__init__.py
pybtocs/interfaces/config.py
pybtocs/interfaces/logger.py
pybtocs/interfaces/manager.py
pybtocs/interfaces/service.py
pybtocs/interfaces/storage.py
pybtocs/interfaces/utils.py
pybtocs/log/__init__.py
pybtocs/log/core.py
pybtocs/plugins/__init__.py
pybtocs/plugins/core.py
pybtocs/rest/__init__.py
pybtocs/rest/const.py
pybtocs/rest/fastapi/__init__.py
pybtocs/rest/fastapi/core.py
pybtocs/rest/fastapi/session.py
pybtocs/security/__init__.py
pybtocs/security/context.py
pybtocs/security/core.py
pybtocs/security/plugins.py
pybtocs/security/auth/__init__.py
pybtocs/security/auth/api_token.py
pybtocs/security/auth/basic.py
pybtocs/security/auth/jwt.py
pybtocs/service/__init__.py
pybtocs/service/context.py
pybtocs/service/core.py
pybtocs/storage/__init__.py
pybtocs/storage/files.py
pybtocs/utils/__init__.py
pybtocs/utils/core.py
pybtocs/utils/yaml.py
pybtocs-0.2.0.dist-info/METADATA
pybtocs-0.2.0.dist-info/WHEEL
pybtocs-0.2.0.dist-info/top_level.txt
pybtocs-0.2.0.dist-info/RECORD
